unit_db_test/__init__.py
unit_db_test/sql_alchemy_driver.py
unit_db_test/testcase.py
unit_db_test/utils.py
unit_db_test-0.1.13.dist-info/LICENSE
unit_db_test-0.1.13.dist-info/METADATA
unit_db_test-0.1.13.dist-info/WHEEL
unit_db_test-0.1.13.dist-info/top_level.txt
unit_db_test-0.1.13.dist-info/RECORD
