Metadata-Version: 2.1
Name: unit-db-test
Version: 0.1.13
Summary: Unittest wrapper focused on making DB integrity tests
Author-email: "@cortze | Mikel Cortes " <cortze@protonmail.com>
License: MIT License
Project-URL: Repository, https://github.com/cortze/unit-db-test
Requires-Python: >=3.8
License-File: LICENSE
Requires-Dist: asynch ==0.2.3
Requires-Dist: build ==1.0.3
Requires-Dist: certifi ==2023.11.17
Requires-Dist: charset-normalizer ==3.3.2
Requires-Dist: ciso8601 ==2.3.1
Requires-Dist: clickhouse-connect ==0.7.0
Requires-Dist: clickhouse-driver ==0.2.6
Requires-Dist: clickhouse-sqlalchemy ==0.3.0
Requires-Dist: greenlet ==2.0.2
Requires-Dist: idna ==3.6
Requires-Dist: leb128 ==1.0.5
Requires-Dist: lz4 ==4.3.3
Requires-Dist: numpy ==1.24.4
Requires-Dist: packaging ==23.1
Requires-Dist: pandas ==2.0.3
Requires-Dist: psycopg2-binary ==2.9.7
Requires-Dist: pyproject-hooks ==1.0.0
Requires-Dist: python-dateutil ==2.8.2
Requires-Dist: python-dotenv ==1.0.0
Requires-Dist: pytz ==2023.3.post1
Requires-Dist: requests ==2.31.0
Requires-Dist: setuptools-scm ==8.0.2
Requires-Dist: six ==1.16.0
Requires-Dist: SQLAlchemy ==2.0.21
Requires-Dist: typing-extensions ==4.8.0
Requires-Dist: tzdata ==2023.3
Requires-Dist: tzlocal ==5.2
Requires-Dist: urllib3 ==2.2.0
Requires-Dist: zstandard ==0.22.0
Requires-Dist: zstd ==1.5.5.1
